LICENSE
MANIFEST.in
README.rst
requirements.txt
setup.py
test-requirements.txt
python_version_info.egg-info/PKG-INFO
python_version_info.egg-info/SOURCES.txt
python_version_info.egg-info/dependency_links.txt
python_version_info.egg-info/requires.txt
python_version_info.egg-info/top_level.txt
tests/__init__.py
version_info/__init__.py
version_info/exceptions.py
version_info/get_version.py